{
  "$schema": "https://schemas.wp.org/trunk/theme.json",
  "version": 2,
  "title": "Anis Blog Child",
  "settings": {
    "color": {
      "palette": [
        { "slug": "brand", "name": "Brand Orange", "color": "#FF7B00" },
        { "slug": "accent", "name": "Accent Tan", "color": "#F4A261" },
        { "slug": "background", "name": "Background Cream", "color": "#FFF8F0" },
        { "slug": "text", "name": "Text Dark", "color": "#2E2E2E" },
        { "slug": "muted", "name": "Muted Green", "color": "#5C715E" }
      ]
    }
  }
}
